raySD/__init__.py
raySD/pipeline/Abstract_Pipeline.py
raySD/pipeline/Stable_Diffusion_IP_Adapter.py
raySD/pipeline/Stable_Diffusion_Lineart.py
raySD/pipeline/Super_Resolution_Pipeline.py
raySD/pipeline/__init__.py
raySD/prompt/__init__.py
raySD/prompt/ancient_costume_prompt.py
raySD/prompt/chibi_prompt.py
raySD/prompt/pencil_art_prompt.py
raySD/pydantic_model/Image_Generate_Model.py
raySD/pydantic_model/Image_Response_Model.py
raySD/pydantic_model/Message_Model.py
raySD/pydantic_model/Stable_Diffusion_IP_Adapter_Model.py
raySD/pydantic_model/Stable_Diffusion_Lineart_Model.py
raySD/pydantic_model/__init__.py
raySD/utils/Enable_xFormers.py
raySD/utils/Lineart_Standard.py
raySD/utils/Preprocess_Resize_Image.py
raySD/utils/__init__.py
raysd-0.2.9.dist-info/METADATA
raysd-0.2.9.dist-info/WHEEL
raysd-0.2.9.dist-info/top_level.txt
raysd-0.2.9.dist-info/RECORD
